django_xchange/__init__.py
django_xchange/admin.py
django_xchange/config.py
django_xchange/constants.py
django_xchange/exceptions.py
django_xchange/models.py
django_xchange/types.py
django_xchange/utils.py
django_xchange/version.py
django_xchange/views.py
django_xchange/brokers/__init__.py
django_xchange/brokers/common.py
django_xchange/brokers/pyoxr.py
django_xchange/management/__init__.py
django_xchange/management/import_data.py
django_xchange/management/utils.py
django_xchange/migrations/0001_initial.py
django_xchange/migrations/__init__.py
django_xchange-0.2.0.dist-info/METADATA
django_xchange-0.2.0.dist-info/WHEEL
django_xchange-0.2.0.dist-info/licenses/LICENSE.md
django_xchange-0.2.0.dist-info/RECORD
