Metadata-Version: 2.4
Name: django-xchange
Version: 0.2.0
Summary: Django currency exchange library
Author-email: Giovanni Bronzini <g.bronzini@gmail.com>
License: K-Tech
License-File: LICENSE.md
Classifier: Environment :: Web Environment
Classifier: Framework :: Django
Classifier: Framework :: Django :: 5.2
Classifier: Intended Audience :: Developers
Classifier: Operating System :: OS Independent
Classifier: Programming Language :: Python :: 3 :: Only
Classifier: Programming Language :: Python :: 3.10
Classifier: Programming Language :: Python :: 3.11
Classifier: Programming Language :: Python :: 3.12
Classifier: Programming Language :: Python :: 3.13
Requires-Python: >=3.10
Requires-Dist: django
Requires-Dist: requests
Provides-Extra: pyoxr
Requires-Dist: pyoxr; extra == 'pyoxr'
